[
  {
    "id": 1,
    "question": "1 × 1 = ?",
    "options": ["1", "2", "3", "4"],
    "correctOptionIndex": 0,
    "difficulty": 1,
    "category": "구구단 1단",
    "parentCategory": "구구단",
    "experienceReward": 10,
    "experiencePenalty": 5
  },
  {
    "id": 2,
    "question": "1 × 2 = ?",
    "options": ["1", "2", "3", "4"],
    "correctOptionIndex": 1,
    "difficulty": 1,
    "category": "구구단 1단",
    "parentCategory": "구구단",
    "experienceReward": 10,
    "experiencePenalty": 5
  },
  {
    "id": 3,
    "question": "2 × 1 = ?",
    "options": ["1", "2", "3", "4"],
    "correctOptionIndex": 1,
    "difficulty": 1,
    "category": "구구단 2단",
    "parentCategory": "구구단",
    "experienceReward": 10,
    "experiencePenalty": 5
  },
  {
    "id": 4,
    "question": "2 × 2 = ?",
    "options": ["2", "3", "4", "5"],
    "correctOptionIndex": 2,
    "difficulty": 1,
    "category": "구구단 2단",
    "parentCategory": "구구단",
    "experienceReward": 10,
    "experiencePenalty": 5
  },
  {
    "id": 5,
    "question": "3 × 1 = ?",
    "options": ["1", "2", "3", "4"],
    "correctOptionIndex": 2,
    "difficulty": 1,
    "category": "구구단 3단",
    "parentCategory": "구구단",
    "experienceReward": 10,
    "experiencePenalty": 5
  },
  {
    "id": 6,
    "question": "4 × 2 = ?",
    "options": ["6", "8", "10", "12"],
    "correctOptionIndex": 1,
    "difficulty": 1,
    "category": "구구단 4단",
    "parentCategory": "구구단",
    "experienceReward": 10,
    "experiencePenalty": 5
  },
  {
    "id": 7,
    "question": "5 × 3 = ?",
    "options": ["10", "15", "20", "25"],
    "correctOptionIndex": 1,
    "difficulty": 1,
    "category": "구구단 5단",
    "parentCategory": "구구단",
    "experienceReward": 10,
    "experiencePenalty": 5
  },
  {
    "id": 8,
    "question": "6 × 4 = ?",
    "options": ["18", "24", "30", "36"],
    "correctOptionIndex": 1,
    "difficulty": 2,
    "category": "구구단 6단",
    "parentCategory": "구구단",
    "experienceReward": 20,
    "experiencePenalty": 10
  },
  {
    "id": 9,
    "question": "7 × 5 = ?",
    "options": ["25", "30", "35", "40"],
    "correctOptionIndex": 2,
    "difficulty": 2,
    "category": "구구단 7단",
    "parentCategory": "구구단",
    "experienceReward": 20,
    "experiencePenalty": 10
  },
  {
    "id": 10,
    "question": "8 × 6 = ?",
    "options": ["42", "48", "54", "60"],
    "correctOptionIndex": 1,
    "difficulty": 2,
    "category": "구구단 8단",
    "parentCategory": "구구단",
    "experienceReward": 20,
    "experiencePenalty": 10
  },
  {
    "id": 11,
    "question": "9 × 7 = ?",
    "options": ["56", "63", "72", "81"],
    "correctOptionIndex": 1,
    "difficulty": 2,
    "category": "구구단 9단",
    "parentCategory": "구구단",
    "experienceReward": 20,
    "experiencePenalty": 10
  },
  {
    "id": 12,
    "question": "미국의 수도는?",
    "options": ["뉴욕", "워싱턴 D.C.", "로스앤젤레스", "시카고"],
    "correctOptionIndex": 1,
    "difficulty": 1,
    "category": "나라 수도 맞히기",
    "parentCategory": "나라 맞히기",
    "experienceReward": 10,
    "experiencePenalty": 5
  },
  {
    "id": 13,
    "question": "프랑스의 수도는?",
    "options": ["파리", "마르세유", "리옹", "니스"],
    "correctOptionIndex": 0,
    "difficulty": 1,
    "category": "나라 수도 맞히기",
    "parentCategory": "나라 맞히기",
    "experienceReward": 10,
    "experiencePenalty": 5
  },
  {
    "id": 14,
    "question": "이 국기는 어느 나라의 국기인가요?",
    "options": ["미국", "영국", "호주", "뉴질랜드"],
    "correctOptionIndex": 0,
    "difficulty": 1,
    "category": "나라 국기 맞히기",
    "parentCategory": "나라 맞히기",
    "experienceReward": 10,
    "experiencePenalty": 5
  },
  {
    "id": 15,
    "question": "이 국기는 어느 나라의 국기인가요?",
    "options": ["독일", "벨기에", "네덜란드", "룩셈부르크"],
    "correctOptionIndex": 0,
    "difficulty": 2,
    "category": "나라 국기 맞히기",
    "parentCategory": "나라 맞히기",
    "experienceReward": 20,
    "experiencePenalty": 10
  }
] 